<?xml version="1.0" standalone="no"?>
<!--
  Openbiz Cubi Application Platform
  LICENSE http://code.google.com/p/openbiz-cubi/wiki/CubiLicense
  Copyright (c) 2005-2011, Openbiz Technology LLC
  Version $Id: UserPrefDO.xml 3375 2012-05-31 06:23:11Z rockyswen@gmail.com $
-->
<BizDataObj Name="UserPrefDO" Description="" Class="BizDataObj" DBName="Default" Table="user_pref" SearchRule="" SortRule="" OtherSQLRule="" Uniqueness="" Stateless="N" IdGeneration="Identity" CacheLifeTime="0">
	<BizFieldList>
        <BizField Name="Id" Column="id"     Type="Number"/>
        <BizField Name="user_id" Column="user_id"    Required="Y" Type="Number"/>
        <BizField Name="name" Column="name" Length="128"   Required="Y" Type="Text"/>
        <BizField Name="value" Column="value" Length="255"   Required="Y" Type="Text"/>
        <BizField Name="type" Column="type" Length="128"   Required="N" Type="Text"/>
		<BizField Name="create_by" Column="create_by" Type="Number" ValueOnCreate="{@profile:Id}"/>
		<BizField Name="create_time" Column="create_time"  Type="Datetime" ValueOnCreate="{date('Y-m-d H:i:s')}"/>
		<BizField Name="update_by" Column="update_by" Type="Number" ValueOnCreate="{@profile:Id}" ValueOnUpdate="{@profile:Id}"/>		
		<BizField Name="update_time" Column="update_time" Type="Datetime" ValueOnCreate="{date('Y-m-d H:i:s')}" ValueOnUpdate="{date('Y-m-d H:i:s')}"/>
	</BizFieldList>
    <TableJoins>
    </TableJoins>
    <ObjReferences>
    </ObjReferences>
</BizDataObj>